{"cameraMode":{"drawMode":0,"name":"Shaded","section":"Shading Mode"},"sceneLighting":true,"audioPlay":false,"sceneViewState":{"m_AlwaysRefresh":false,"showFog":true,"showSkybox":true,"showFlares":true,"showImageEffects":true,"showParticleSystems":true,"showVisualEffectGraphs":true,"m_FxEnabled":true},"in2DMode":false,"pivot":{"x":44.432640075683597,"y":-14.936553001403809,"z":11.798873901367188},"rotation":{"x":-0.1885589361190796,"y":-0.4685779809951782,"z":0.10312142968177796,"w":-0.856907844543457},"size":34.337646484375,"orthographic":false}